wellcard.py
wellcard-0.0.4.dist-info/METADATA
wellcard-0.0.4.dist-info/WHEEL
wellcard-0.0.4.dist-info/top_level.txt
wellcard-0.0.4.dist-info/RECORD
